jrpyvis/__init__.py
jrpyvis/__version__.py
jrpyvis/data/README.md
jrpyvis/data/car_insurance.zip
jrpyvis/data/csv_data.csv
jrpyvis/data/diamonds.zip
jrpyvis/data/exercise.zip
jrpyvis/data/flights.zip
jrpyvis/data/healthexp.zip
jrpyvis/data/insurance.zip
jrpyvis/data/iris.zip
jrpyvis/data/movies.zip
jrpyvis/data/penguins.zip
jrpyvis/data/planets.zip
jrpyvis/data/tabsep_data.csv
jrpyvis/data/titanic.xlsx
jrpyvis/data.py
jrpyvis/data_raw/README.md
jrpyvis/solutions/example_solution.mplstyle
jrpyvis/solutions.py
jrpyvis-1.0.5.dist-info/METADATA
jrpyvis-1.0.5.dist-info/WHEEL
jrpyvis-1.0.5.dist-info/RECORD
