Metadata-Version: 2.3
Name: jrpyvis
Version: 1.0.5
Summary: Jumping Rivers: Data Visualisation with Python
Author: Jumping Rivers
Author-email: info@jumpingrivers.com
Requires-Python: >=3.10
Classifier: Programming Language :: Python :: 3
Classifier: Programming Language :: Python :: 3.10
Classifier: Programming Language :: Python :: 3.11
Classifier: Programming Language :: Python :: 3.12
Classifier: Programming Language :: Python :: 3.13
Requires-Dist: matplotlib (==3.10.0)
Requires-Dist: numpy (>=2.0,<3.0)
Requires-Dist: pandas (>=2.2.0,<3.0.0)
Requires-Dist: seaborn (>=0.13.0,<0.14.0)
